envrypt
