Metadata-Version: 2.1
Name: envrypt
Version: 0.0.2
Summary: Python tool/library designed to secure environment variables by encrypting them both in disk and memory.
Author: Robin Syihab
Author-email: robinsyihab@gmail.com
License: MIT
Classifier: Programming Language :: Python :: 3
Classifier: License :: OSI Approved :: MIT License
Classifier: Operating System :: OS Independent
Requires-Python: >=2.7
License-File: LICENSE
